inyaml/__init__.py
inyaml/construction.py
inyaml/executable_construction.py
inyaml/functions.py
inyaml/instantiable_construction.py
inyaml/namespace.py
inyaml/special_keys.py
inyaml/yaml_import_renames.py
inyaml-0.0.1.2.dist-info/LICENSE
inyaml-0.0.1.2.dist-info/METADATA
inyaml-0.0.1.2.dist-info/WHEEL
inyaml-0.0.1.2.dist-info/top_level.txt
inyaml-0.0.1.2.dist-info/RECORD
