Metadata-Version: 2.1
Name: inyaml
Version: 0.0.1.2
Summary: A library based on `PyYAML` that promises to parse YAML documents and produce Python objects, for executing Python code within YAML documents and instantiating Python objects based on YAML arguments.
Author-email: Caewinix <Caewinix@yeah.net>
Project-URL: Homepage, https://github.com/Caewinix/inyaml
Project-URL: Bug Tracker, https://github.com/Caewinix/inyaml/issues
Classifier: Programming Language :: Python :: 3
Classifier: License :: OSI Approved :: MIT License
Classifier: Operating System :: OS Independent
Requires-Python: >=3.7
License-File: LICENSE
Requires-Dist: lark >=0.6.0
Requires-Dist: PyYAML >=3.13
